<?xml version="1.0" encoding="UTF-8"?>
<objects serializationModel="Studio.02.03.00">
	<object class="AudioFile" id="{136629f4-7bde-4cb4-8972-0e04d4234c4d}">
		<property name="assetPath">
			<value>SFX/Character/MTF/Epsilon11/Stop3.ogg</value>
		</property>
		<property name="frequencyInKHz">
			<value>44.0999985</value>
		</property>
		<property name="channelCount">
			<value>2</value>
		</property>
		<property name="length">
			<value>1.0081632653061225</value>
		</property>
		<relationship name="masterAssetFolder">
			<destination>{1c687daf-b876-4ac5-9b0c-e1fc361963f3}</destination>
		</relationship>
	</object>
</objects>
